mongollect/__init__.py
mongollect/core.py
mongollect-0.1.0.dist-info/METADATA
mongollect-0.1.0.dist-info/WHEEL
mongollect-0.1.0.dist-info/top_level.txt
mongollect-0.1.0.dist-info/RECORD
