Metadata-Version: 2.4
Name: mongollect
Version: 0.1.0
Summary: Tiny MongoDB collection injector decorator for Python classes.
Author-email: "Kaene K. Lebakeng" <kaenekarabolebakeng@gmail.com>
License-Expression: MIT
Requires-Python: >=3.8
